jupyter_singleton/__init__.py
jupyter_singleton/debugredirect.html
jupyter_singleton/displaydatahook.py
jupyter_singleton/dummylauncher.py
jupyter_singleton/handlers.py
jupyter_singleton/serverlauncher.py
jupyter_singleton/singletonapp.py
jupyter_singleton/singletonipkernel.py
jupyter_singleton/singletonkernelmanager.py
jupyter_singleton/wrapper.html
jupyter_singleton/config/__init__.py
jupyter_singleton/direct/__init__.py
jupyter_singleton-0.1.0.dist-info/LICENSE
jupyter_singleton-0.1.0.dist-info/METADATA
jupyter_singleton-0.1.0.dist-info/WHEEL
jupyter_singleton-0.1.0.dist-info/top_level.txt
jupyter_singleton-0.1.0.dist-info/RECORD
