Metadata-Version: 2.1
Name: jupyter-singleton
Version: 0.1.0
Summary: jupyter notebook wrapper for making output cells available outside of notebook
Home-page: https://github.com/EricMende/jupyter_singleton
Author: Eric Mende
Author-email: em@bc-potsdam.de
License: MIT License
Platform: UNKNOWN
Classifier: License :: OSI Approved :: MIT License
Classifier: Topic :: Utilities
Classifier: Programming Language :: Python :: 3
Classifier: Operating System :: OS Independent
Classifier: Natural Language :: English
Requires-Python: >=3.6
Requires-Dist: ipykernel (>=5.1.1)
Requires-Dist: IPython (>=7.5.0)
Requires-Dist: jinja2 (>=2.10.1)
Requires-Dist: jupyter-client (>=5.2.4)
Requires-Dist: jupyter-nbextensions-configurator (>=0.4.1)
Requires-Dist: notebook (>=5.7.8)
Requires-Dist: tornado (>=6.0.2)
